stressor/__init__.py
stressor/cli_common.py
stressor/config_manager.py
stressor/context_stack.py
stressor/plugin_manager.py
stressor/run_manager.py
stressor/session_manager.py
stressor/statistic_manager.py
stressor/stressor_cli.py
stressor/util.py
stressor/convert/__init__.py
stressor/convert/har_converter.py
stressor/convert/scenario.yaml.tmpl
stressor/convert/sequence.yaml.tmpl
stressor/convert/users.yaml.tmpl
stressor/monitor/__init__.py
stressor/monitor/server.py
stressor/monitor/htdocs/favicon.ico
stressor/monitor/htdocs/index.html
stressor/monitor/htdocs/info_red_16.png
stressor/monitor/htdocs/info_red_222.png
stressor/monitor/htdocs/logo_1_285x285.png
stressor/monitor/htdocs/logo_2_285x285.png
stressor/monitor/htdocs/logo_3_285x285.png
stressor/monitor/htdocs/logo_4_285x285.png
stressor/monitor/htdocs/logo_57x57.png
stressor/monitor/htdocs/monitor.js
stressor/monitor/htdocs/stage_done_error.png
stressor/monitor/htdocs/stage_done_ok.png
stressor/monitor/htdocs/stage_idle_1.png
stressor/monitor/htdocs/stage_ready.png
stressor/monitor/htdocs/stage_running_error.png
stressor/monitor/htdocs/stage_running_ok.png
stressor/monitor/htdocs/status_bad.png
stressor/monitor/htdocs/status_critical.png
stressor/monitor/htdocs/status_sleeping.png
stressor/monitor/htdocs/stressor_100x100.png
stressor/monitor/htdocs/stressor_2.png
stressor/monitor/htdocs/stressor_3.png
stressor/monitor/htdocs/stressor_32x32.png
stressor/monitor/htdocs/stressor_48x48.png
stressor/monitor/htdocs/style.css
stressor/plugins/__init__.py
stressor/plugins/base.py
stressor/plugins/common.py
stressor/plugins/http_activities.py
stressor/plugins/script_activities.py
stressor-0.6.0.data/data/CHANGELOG.md
tests/__init__.py
tests/conftest.py
tests/mock_server.py
tests/test_config_manager.py
tests/test_context_stack.py
tests/test_convert.py
tests/test_plugin_manager.py
tests/test_run_manager.py
tests/test_script_activities.py
tests/test_util.py
tests/util.py
stressor-0.6.0.dist-info/LICENSE.txt
stressor-0.6.0.dist-info/METADATA
stressor-0.6.0.dist-info/WHEEL
stressor-0.6.0.dist-info/entry_points.txt
stressor-0.6.0.dist-info/top_level.txt
stressor-0.6.0.dist-info/RECORD
