Metadata-Version: 2.1
Name: stressor
Version: 0.6.0
Summary: Stress-test your web app
Home-page: https://github.com/mar10/stressor
Author: Martin Wendt
Author-email: stressor@wwwendt.de
Maintainer: Martin Wendt
Maintainer-email: stressor@wwwendt.de
License: MIT
Project-URL: Bug Tracker, https://github.com/mar10/stressor/issues
Project-URL: Source Code, https://github.com/mar10/stressor
Project-URL: Documentation, https://stressor.readthedocs.io
Project-URL: Download, https://github.com/mar10/stressor/releases/latest
Keywords: web,server,load,test,stress
Classifier: Development Status :: 4 - Beta
Classifier: Environment :: Console
Classifier: Intended Audience :: Developers
Classifier: Intended Audience :: Information Technology
Classifier: Intended Audience :: System Administrators
Classifier: License :: OSI Approved :: MIT License
Classifier: Operating System :: OS Independent
Classifier: Programming Language :: Python
Classifier: Programming Language :: Python :: 3
Classifier: Programming Language :: Python :: 3 :: Only
Classifier: Programming Language :: Python :: 3.9
Classifier: Programming Language :: Python :: 3.10
Classifier: Programming Language :: Python :: 3.11
Classifier: Programming Language :: Python :: 3.12
Classifier: Topic :: Internet :: WWW/HTTP
Classifier: Topic :: Internet :: WWW/HTTP :: Dynamic Content
Classifier: Topic :: Internet :: WWW/HTTP :: HTTP Servers
Classifier: Topic :: Software Development :: Libraries :: Python Modules
Classifier: Topic :: Software Development :: Quality Assurance
Classifier: Topic :: Software Development :: Testing
Classifier: Topic :: Software Development :: Testing :: Traffic Generation
License-File: LICENSE.txt
Requires-Dist: fabulist
Requires-Dist: lxml
Requires-Dist: python-dateutil
Requires-Dist: PyYAML
Requires-Dist: requests
Requires-Dist: snazzy
